{"id":"..\\node_modules\\faker\\lib\\locales\\ko\\company\\index.js","dependencies":[{"name":"D:\\REACT\\FRONTEND_MASTERS\\AdopMe\\node_modules\\faker\\package.json","includedInParent":true,"mtime":1572531754003},{"name":"D:\\REACT\\FRONTEND_MASTERS\\AdopMe\\package.json","includedInParent":true,"mtime":1572637321830},{"name":"./suffix","loc":{"line":3,"column":25},"parent":"D:\\REACT\\FRONTEND_MASTERS\\AdopMe\\node_modules\\faker\\lib\\locales\\ko\\company\\index.js","resolved":"D:\\REACT\\FRONTEND_MASTERS\\AdopMe\\node_modules\\faker\\lib\\locales\\ko\\company\\suffix.js"},{"name":"./prefix","loc":{"line":4,"column":25},"parent":"D:\\REACT\\FRONTEND_MASTERS\\AdopMe\\node_modules\\faker\\lib\\locales\\ko\\company\\index.js","resolved":"D:\\REACT\\FRONTEND_MASTERS\\AdopMe\\node_modules\\faker\\lib\\locales\\ko\\company\\prefix.js"},{"name":"./name","loc":{"line":5,"column":23},"parent":"D:\\REACT\\FRONTEND_MASTERS\\AdopMe\\node_modules\\faker\\lib\\locales\\ko\\company\\index.js","resolved":"D:\\REACT\\FRONTEND_MASTERS\\AdopMe\\node_modules\\faker\\lib\\locales\\ko\\company\\name.js"}],"generated":{"js":"var company = {};\nmodule['exports'] = company;\ncompany.suffix = require(\"./suffix\");\ncompany.prefix = require(\"./prefix\");\ncompany.name = require(\"./name\");\n","map":{"mappings":[{"source":"..\\node_modules\\faker\\lib\\locales\\ko\\company\\index.js","original":{"line":1,"column":0},"generated":{"line":1,"column":0}},{"source":"..\\node_modules\\faker\\lib\\locales\\ko\\company\\index.js","original":{"line":2,"column":0},"generated":{"line":2,"column":0}},{"source":"..\\node_modules\\faker\\lib\\locales\\ko\\company\\index.js","original":{"line":3,"column":0},"generated":{"line":3,"column":0}},{"source":"..\\node_modules\\faker\\lib\\locales\\ko\\company\\index.js","original":{"line":4,"column":0},"generated":{"line":4,"column":0}},{"source":"..\\node_modules\\faker\\lib\\locales\\ko\\company\\index.js","original":{"line":5,"column":0},"generated":{"line":5,"column":0}},{"source":"..\\node_modules\\faker\\lib\\locales\\ko\\company\\index.js","original":{"line":6,"column":0},"generated":{"line":6,"column":0}}],"sources":{"..\\node_modules\\faker\\lib\\locales\\ko\\company\\index.js":"var company = {};\nmodule['exports'] = company;\ncompany.suffix = require(\"./suffix\");\ncompany.prefix = require(\"./prefix\");\ncompany.name = require(\"./name\");\n"},"lineCount":6}},"hash":"09ced9922edef174c437a245698300ba","cacheData":{"env":{}}}